dictcc/__init__.py
dictcc/cli.py
dictcc/scraper.py
dictcc/utils.py
dictcc_cli-1.0.dist-info/LICENSE
dictcc_cli-1.0.dist-info/METADATA
dictcc_cli-1.0.dist-info/WHEEL
dictcc_cli-1.0.dist-info/entry_points.txt
dictcc_cli-1.0.dist-info/RECORD
